[
    {
        "name": "SanDisk Ultra 128GB SDXC UHS-I Memory Card up to 80MB/s",
        "price": "45.89",
        "description": "Ultra- fast cards (2). Take Ultra- fast cards (2). Take Ultra- fast cards (2). Take Ultra- fast cards (2). Take Ultra- fast cards (2). ",
        "ratings": 4.5,
        "images": [
            {
                "public_id": "products/tzfsnrli3szrdnb4jgge",
                "url": "http://res.cloudinary.com/shopit/image/upload/v1606231282/products/tzfsnrli3szrdnb4jgge.jpg"
            }
        ],
        "category": "Electronics",
        "seller": "Ebay",
        "stock": 50,
        "numOfReviews": 32,
        "reviews": []
    },
    {
        "name": "SanDisk Ultra 128GB SDXC UHS-I Memory Card up to 80MB/s",
        "price": "45.89",
        "description": "Ultra- fast cards (2). Take Ultra- fast cards (2). Take Ultra- fast cards (2). Take Ultra- fast cards (2). Take Ultra- fast cards (2). ",
        "ratings": 4.5,
        "images": [
            {
                "public_id": "products/tzfsnrli3szrdnb4jgge",
                "url": "http://res.cloudinary.com/shopit/image/upload/v1606231282/products/tzfsnrli3szrdnb4jgge.jpg"
            }
        ],
        "category": "Electronics",
        "seller": "Ebay",
        "stock": 50,
        "numOfReviews": 32,
        "reviews": []
    },
    {
        "name": "SanDisk Ultra 128GB SDXC UHS-I Memory Card up to 80MB/s",
        "price": "45.89",
        "description": "Ultra- fast cards (2). Take Ultra- fast cards (2). Take Ultra- fast cards (2). Take Ultra- fast cards (2). Take Ultra- fast cards (2). ",
        "ratings": 4.5,
        "images": [
            {
                "public_id": "products/tzfsnrli3szrdnb4jgge",
                "url": "http://res.cloudinary.com/shopit/image/upload/v1606231282/products/tzfsnrli3szrdnb4jgge.jpg"
            }
        ],
        "category": "Electronics",
        "seller": "Ebay",
        "stock": 50,
        "numOfReviews": 32,
        "reviews": []
    },
    {
        "name": "Asus Laptop",
        "price": "45.89",
        "description": "Ultra- fast cards (2). Take Ultra- fast cards (2). Take Ultra- fast cards (2). Take Ultra- fast cards (2). Take Ultra- fast cards (2). ",
        "ratings": 4.5,
        "images": [
            {
                "public_id": "products/tzfsnrli3szrdnb4jgge",
                "url": "http://res.cloudinary.com/shopit/image/upload/v1606231282/products/tzfsnrli3szrdnb4jgge.jpg"
            }
        ],
        "category": "Laptop",
        "seller": "Ebay",
        "stock": 50,
        "numOfReviews": 32,
        "reviews": []
    }
]